{
  "stock": [
    {
      "time": 145906,
      "date": 20220831,
      "price": 11.920000000000002,
      "open": 12.530000000000001,
      "yclose": 13.08,
      "high": 13.42,
      "low": 12.979999999999999,
      "vol": 161144958,
      "amount": 2038378496,
      "amplitude": 3.3653846153846154,
      "increase": 1.8429487179487178,
      "exchangerate": 0.8304066791583011,
      "buy": [
        {
          "price": 12.74,
          "vol": 28014
        },
        {
          "price": 0,
          "vol": 0
        },
        {
          "price": 0,
          "vol": 0
        },
        {
          "price": 0,
          "vol": 0
        },
        {
          "price": 0,
          "vol": 0
        }
      ],
      "sell": [
        {
          "price": 12.74,
          "vol": 28014
        },
        {
          "price": 0,
          "vol": 3361
        },
        {
          "price": 0,
          "vol": 0
        },
        {
          "price": 0,
          "vol": 0
        },
        {
          "price": 0,
          "vol": 0
        }
      ],
      "week": {
        "week1": 2.499999999999991,
        "week4": 5.652535328345798,
        "week13": -8.624715966862029,
        "week26": -20.278864947058917,
        "week52": -26.817080208753797
      },
      "symbol": "000001.sz",
      "name": "平安银行"
    }
  ],
  "start": 0,
  "end": 100,
  "count": 1,
  "ticket": 0,
  "version": "HQ.Stock 2.0",
  "message": null,
  "code": 0,
  "servertime": "2022-08-31 14:59:24"
}
